cinipy/__init__.py
cinipy/cinipy.py
cinipy-0.0.2.dist-info/METADATA
cinipy-0.0.2.dist-info/WHEEL
cinipy-0.0.2.dist-info/top_level.txt
cinipy-0.0.2.dist-info/RECORD
